siosocks/__init__.py
siosocks/__main__.py
siosocks/exceptions.py
siosocks/interface.py
siosocks/protocol.py
siosocks/sansio.py
siosocks/io/__init__.py
siosocks/io/asyncio.py
siosocks/io/const.py
siosocks/io/socket.py
siosocks/io/trio.py
siosocks-0.3.0.dist-info/METADATA
siosocks-0.3.0.dist-info/WHEEL
siosocks-0.3.0.dist-info/license.txt
siosocks-0.3.0.dist-info/top_level.txt
siosocks-0.3.0.dist-info/RECORD
