Metadata-Version: 2.1
Name: siosocks
Version: 0.3.0
Summary: sans-io socks proxy client/server with couple io backends
Home-page: https://github.com/pohmelie/siosocks
Author: pohmelie
Author-email: multisosnooley@gmail.com
License: MIT
Classifier: Programming Language :: Python
Classifier: Programming Language :: Python :: 3
Requires-Python: >=3.8
License-File: license.txt
Provides-Extra: dev
Requires-Dist: pytest ; extra == 'dev'
Requires-Dist: pytest-cov ; extra == 'dev'
Requires-Dist: pytest-asyncio ; extra == 'dev'
Requires-Dist: trio ; extra == 'dev'
Requires-Dist: pytest-trio ; extra == 'dev'
Provides-Extra: trio
Requires-Dist: trio ; extra == 'trio'
